CEIT/EFEM.py
CEIT/EITPlotter.py
CEIT/EJAC.py
CEIT/FEMBasic.py
CEIT/Simulator.py
CEIT/Solver.py
CEIT/__init__.py
CEIT/readmesh.py
CEIT/datahandler/Comparator.py
CEIT/datahandler/Data.py
CEIT/datahandler/DataHandler.py
CEIT/datahandler/Dataset.py
CEIT/datahandler/__init__.py
CEIT/models/__init__.py
CEIT/models/mesh.py
CEIT-0.0.1.dist-info/LICENSE
CEIT-0.0.1.dist-info/METADATA
CEIT-0.0.1.dist-info/WHEEL
CEIT-0.0.1.dist-info/top_level.txt
CEIT-0.0.1.dist-info/RECORD
