Metadata-Version: 2.1
Name: CEIT
Version: 0.0.1
Summary: Python Package for EIT(Electric Impedance Tomography)-like problems using Gauss-Newton method.
Home-page: https://github.com/zehao99/CEIT
Author: Li Zehao
Author-email: zehaoli99@gmail.com
License: UNKNOWN
Platform: UNKNOWN
Classifier: Programming Language :: Python :: 3
Classifier: License :: OSI Approved :: MIT License
Classifier: Operating System :: OS Independent
Requires-Dist: numpy
Requires-Dist: matplotlib
Requires-Dist: progressbar2
